pysmart_exporter/__init__.py
pysmart_exporter/__main__.py
pysmart_exporter/collector.py
pysmart_exporter/version.py
pysmart_exporter-0.4.1.dist-info/licenses/LICENSE.md
pysmart_exporter-0.4.1.dist-info/METADATA
pysmart_exporter-0.4.1.dist-info/WHEEL
pysmart_exporter-0.4.1.dist-info/entry_points.txt
pysmart_exporter-0.4.1.dist-info/top_level.txt
pysmart_exporter-0.4.1.dist-info/RECORD
