Metadata-Version: 2.4
Name: pySMART-exporter
Version: 0.4.1
Summary: A Prometheus PySMART exporter
Author-email: Rafael Leira <rafael.leira@naudit.es>
License: BSD-3-Clause
Project-URL: homepage, https://repo1.naudit.es/theseus/pysmart-exporter
Keywords: prometheus,SMART,exporter,monitoring
Classifier: Development Status :: 4 - Beta
Classifier: Intended Audience :: Developers
Classifier: Intended Audience :: System Administrators
Classifier: License :: OSI Approved :: BSD License
Classifier: Operating System :: OS Independent
Classifier: Programming Language :: Python
Classifier: Programming Language :: Python :: 3
Classifier: Topic :: Software Development
Classifier: Topic :: Software Development :: Libraries
Classifier: Topic :: Software Development :: Libraries :: Python Modules
License-File: LICENSE.md
Requires-Dist: prometheus-client
Requires-Dist: pySMART>=1.3.0
Provides-Extra: dev
Requires-Dist: pytest; extra == "dev"
Requires-Dist: pytest-cov; extra == "dev"
Requires-Dist: mypy; extra == "dev"
Requires-Dist: types-tabulate; extra == "dev"
Requires-Dist: types-six; extra == "dev"
Requires-Dist: pdoc; extra == "dev"
Dynamic: license-file
